pereader.py
pereader-9.8.2020.dist-info/LICENSE
pereader-9.8.2020.dist-info/METADATA
pereader-9.8.2020.dist-info/WHEEL
pereader-9.8.2020.dist-info/top_level.txt
pereader-9.8.2020.dist-info/RECORD
