Metadata-Version: 2.1
Name: pereader
Version: 9.8.2020
Summary: A lightweight Python module for parsing portable executable files.
Home-page: https://github.com/matthewPeart/PEReader
Author: Matthew Peart
License: MIT License
Keywords: pe,parser,exe,dll,pereader
Platform: UNKNOWN
Classifier: Programming Language :: Python :: 3
Classifier: Programming Language :: Python :: 3.6
Classifier: Programming Language :: Python :: 3.7
Classifier: Programming Language :: Python :: 3.8
Classifier: Operating System :: OS Independent
